callspectpy_cli.py
callspectpy/__init__.py
callspectpy/main.py
callspectpy-0.1.3.dist-info/DESCRIPTION.rst
callspectpy-0.1.3.dist-info/METADATA
callspectpy-0.1.3.dist-info/RECORD
callspectpy-0.1.3.dist-info/WHEEL
callspectpy-0.1.3.dist-info/entry_points.txt
callspectpy-0.1.3.dist-info/metadata.json
callspectpy-0.1.3.dist-info/top_level.txt
examples/async-using-api.py
examples/async.py
