Metadata-Version: 2.0
Name: callspectpy
Version: 0.1.3
Summary: Collects execution data from python script
Home-page: https://github.com/xliiv/callspect
Author: xliiv
Author-email: tymoteusz.jankowski@gmail.com
License: MIT
Platform: UNKNOWN
Classifier: Programming Language :: Python :: 3
Requires-Python: >=3.5
